{"":{"data":{"114":{"end":"399","title":"\u3057\u306a\u3051\u308c\u3070\u306a\u3089\u306a\u3044","desc":""},"400":{"end":"498","title":"\u3084\u308a\u6b8b\u3057","desc":""},"790":{"end":"893","title":"\u307e\u3068\u3081","desc":""}},"ip":null},"42bcca4a91fd969442728bcaeff3485d":{"data":"{\"114\":{\"end\":399,\"title\":\"\u3057\u306a\u3051\u308c\u3070\u306a\u3089\u306a\u3044\",\"desc\":\"\"},\"400\":{\"end\":498,\"title\":\"\u3084\u308a\u6b8b\u3057\",\"desc\":\"\"},\"790\":{\"end\":893,\"title\":\"\u307e\u3068\u3081\",\"desc\":\"\"}}","ip":null}}